HaloPSA/Halo.py
HaloPSA/__init__.py
halopsa-2.0.0.dist-info/licenses/LICENSE
halopsa-2.0.0.dist-info/METADATA
halopsa-2.0.0.dist-info/WHEEL
halopsa-2.0.0.dist-info/top_level.txt
halopsa-2.0.0.dist-info/RECORD
