Metadata-Version: 2.4
Name: HaloPSA
Version: 2.0.0
Summary: Python wrapper for the HaloPSA API
Author-email: Fryan O <FryanO@proton.me>
Project-URL: Homepage, https://github.com/ItsJustAGitHubMichealWhosGonnaSeeIt5Ppl/HaloPSA-API
Project-URL: Issues, https://github.com/ItsJustAGitHubMichealWhosGonnaSeeIt5Ppl/HaloPSA-API/issues
Keywords: HaloPSA,HaloPSA API
Classifier: Programming Language :: Python :: 3
Classifier: License :: OSI Approved :: GNU Affero General Public License v3
Classifier: Operating System :: OS Independent
Classifier: Development Status :: 2 - Pre-Alpha
Requires-Python: >=3.10
License-File: LICENSE
Requires-Dist: requests>=2.32.3
Dynamic: license-file
